{
	"name": "DelimitedText1",
	"properties": {
		"linkedServiceName": {
			"referenceName": "AzureBlobStorage1",
			"type": "LinkedServiceReference"
		},
		"annotations": [],
		"type": "DelimitedText",
		"typeProperties": {
			"location": {
				"type": "AzureBlobStorageLocation",
				"container": "atracacaofato"
			},
			"columnDelimiter": ";",
			"escapeChar": "\\",
			"firstRowAsHeader": true,
			"quoteChar": "\""
		},
		"schema": [
			{
				"name": "IDAtracacao;CDTUP;IDBerco;Berço;Porto Atracação;Apelido Instalação Portuária;Complexo Portuário;Tipo da Autoridade Portuária;Data Atracação;Data Chegada;Data Desatracação;Data Início Operação;Data Término Operação;Ano;Mes;Tipo de Operação;Tipo de Navegação da Atracação;Nacionalidade do Armador;FlagMCOperacaoAtracacao;Terminal;Município;UF;SGUF;Região Geográfica;Nº da Capitania;Nº do IMO",
				"type": "String"
			}
		]
	}
}